{
  "baseFingerprint": "b4a4a7941e0ce43f8e07123f70bcc017bd1b394b4ca890dc40608d797f09e958",
  "baseUpdatedAt": "2026-02-04T05:36:55.805Z",
  "ops": [
    {
      "op": "set",
      "path": "blocks.page-meta.copy.title",
      "value": "Funciones de la cuenta regresiva - Clickeen"
    },
    {
      "op": "set",
      "path": "blocks.page-meta.copy.description",
      "value": "Explora las funciones del widget de cuenta regresiva."
    },
    {
      "op": "set",
      "path": "blocks.hero.copy.headline",
      "value": "Funciones de cuenta atrás"
    },
    {
      "op": "set",
      "path": "blocks.hero.copy.subheadline",
      "value": "Todo lo que necesitas para crear urgencia e impulsar la acción."
    }
  ],
  "v": 1
}
